.coveragerc
.gitignore
.pre-commit-config.yaml
.readthedocs.yml
AUTHORS.rst
CHANGES.rst
Dockerfile
LICENSE.txt
README.md
install_requirements.sh
pypi_index.zip
rdocs-requirements.txt
requirements.txt
setup.cfg
setup.py
test-requirements.txt
version.py
.github/ISSUE_TEMPLATE/bug-report.md
.github/ISSUE_TEMPLATE/config.yml
.github/workflows/benchmark_default_branch.yml
.github/workflows/deploy.yml
.github/workflows/stylecheck.yml
.github/workflows/test.yml
.github/workflows/test_all.yml
binder/requirements.txt
docs/Makefile
docs/authors.rst
docs/changes.rst
docs/conf.py
docs/index.rst
docs/license.rst
docs/_static/.gitignore
docs/_static/theme_override.css
docs/_templates/module_functions_template.rst
docs/api/modules.rst
docs/api/tsfresh.convenience.rst
docs/api/tsfresh.examples.rst
docs/api/tsfresh.feature_extraction.rst
docs/api/tsfresh.feature_selection.rst
docs/api/tsfresh.rst
docs/api/tsfresh.scripts.rst
docs/api/tsfresh.transformers.rst
docs/api/tsfresh.utilities.rst
docs/images/feature_extraction_process_20160815_mc_1.png
docs/images/introduction_ts_exa.png
docs/images/introduction_ts_exa_features.png
docs/images/rolling_mechanism_1.png
docs/images/rolling_mechanism_2.png
docs/images/rolling_mechanism_drawio_template.xml
docs/images/ts_example_robot_failures_fail.png
docs/images/ts_example_robot_failures_nofail.png
docs/images/tsfresh_logo.svg
docs/text/data_formats.rst
docs/text/faq.rst
docs/text/feature_calculation.rst
docs/text/feature_extraction_settings.rst
docs/text/feature_filtering.rst
docs/text/forecasting.rst
docs/text/how_to_add_custom_feature.rst
docs/text/how_to_contribute.rst
docs/text/introduction.rst
docs/text/large_data.rst
docs/text/list_of_features.rst
docs/text/quick_start.rst
docs/text/sklearn_transformers.rst
docs/text/tsfresh_on_a_cluster.rst
notebooks/advanced/05 Timeseries Forecasting (multiple ids).ipynb
notebooks/advanced/compare-runtimes-of-feature-calculators.ipynb
notebooks/advanced/feature_extraction_with_datetime_index.ipynb
peritus_tsfresh.egg-info/PKG-INFO
peritus_tsfresh.egg-info/SOURCES.txt
peritus_tsfresh.egg-info/dependency_links.txt
peritus_tsfresh.egg-info/requires.txt
peritus_tsfresh.egg-info/top_level.txt
