Metadata-Version: 2.1
Name: peritus-tsfresh
Version: 1.0.0
Summary: tsfresh extracts relevant characteristics from time series
Home-page: https://github.com/blue-yonder/tsfresh
Author: Maximilian Christ, Nils Braun, Julius Neuffer
Author-email: max.christ@me.com
License: MIT
Classifier: Development Status :: 4 - Beta
Classifier: Programming Language :: Python
Classifier: Programming Language :: Python :: 3
Classifier: Programming Language :: Python :: 3.7
Classifier: Programming Language :: Python :: 3.8
Classifier: Programming Language :: Python :: 3.9
Classifier: Programming Language :: Python :: 3 :: Only
Classifier: Operating System :: Unix
Classifier: Operating System :: Microsoft :: Windows
Classifier: Operating System :: MacOS
Classifier: Intended Audience :: Science/Research
Classifier: Topic :: Scientific/Engineering
Classifier: Topic :: Software Development
Requires-Python: >=3.7
License-File: LICENSE.txt
License-File: AUTHORS.rst
